zeyrek/__init__.py
zeyrek/attributes.py
zeyrek/conditions.py
zeyrek/formatters.py
zeyrek/lexicon.py
zeyrek/lexicon_helpers.py
zeyrek/morphology.py
zeyrek/morphotactics.py
zeyrek/rulebasedanalyzer.py
zeyrek/tr.py
zeyrek/resources/tr/abbreviations.dict
zeyrek/resources/tr/first-10K
zeyrek/resources/tr/informal.dict
zeyrek/resources/tr/item-groups.txt
zeyrek/resources/tr/lexicon.bin
zeyrek/resources/tr/locations-tr.dict
zeyrek/resources/tr/master-dictionary.dict
zeyrek/resources/tr/non-tdk.dict
zeyrek/resources/tr/person-names.dict
zeyrek/resources/tr/proper-from-corpus.dict
zeyrek/resources/tr/proper-ignore
zeyrek/resources/tr/proper.dict
zeyrek/resources/tr/special-dictionary-item-root-suffix-data
zeyrek/resources/tr/tdk-obsolete.dict
zeyrek/resources/tr/turkish-ordinal-numbers.txt
zeyrek/resources/tr/phonetics/english-letter-names.txt
zeyrek/resources/tr/phonetics/english-phones-to-turkish.txt
zeyrek/resources/tr/phonetics/turkish-letter-names.txt
zeyrek/resources/tr/phonetics/turkish-letter-pronunciation.txt
zeyrek-0.1.3.dist-info/AUTHORS.rst
zeyrek-0.1.3.dist-info/LICENSE
zeyrek-0.1.3.dist-info/METADATA
zeyrek-0.1.3.dist-info/WHEEL
zeyrek-0.1.3.dist-info/top_level.txt
zeyrek-0.1.3.dist-info/RECORD
