Metadata-Version: 2.1
Name: zeyrek
Version: 0.1.3
Summary: Python morphological analyzer and lemmatizer for Turkish
Home-page: https://github.com/obulat/zeyrek
Author: Olga Bulat
Author-email: obulat@gmail.com
License: MIT license
Keywords: zeyrek
Classifier: Development Status :: 3 - Alpha
Classifier: Intended Audience :: Developers
Classifier: License :: OSI Approved :: MIT License
Classifier: Natural Language :: English
Classifier: Programming Language :: Python :: 3.9
Classifier: Programming Language :: Python :: 3.10
License-File: LICENSE
License-File: AUTHORS.rst
